README.txt
pypi.sh
setup.py
wxTerminal/Singleton.py
wxTerminal/__init__.py
wxTerminal/version.py
wxTerminal/wxSerialConfigDialog.py
wxTerminal/wxSerialConfigDialog.wxg.xml
wxTerminal/wxTerminal.py
wxTerminal/wxTerminal.wxg.xml
wxTerminal/wxTerminalMP.py
wxTerminal/wxtMsg.py
wxTerminal.egg-info/PKG-INFO
wxTerminal.egg-info/SOURCES.txt
wxTerminal.egg-info/dependency_links.txt
wxTerminal.egg-info/requires.txt
wxTerminal.egg-info/top_level.txt