Metadata-Version: 1.0
Name: wxTerminal
Version: 1.4
Summary: A simple cross platform serial terminal in pure wxPython
Home-page: http://pypi.python.org/pypi/wxTerminal
Author: Jason Morgan
Author-email: pypi@cropwell.net
License: BSD
Keywords: Serial Terminal wx
Platform: UNKNOWN
Classifier: Development Status :: 3 - Alpha
Classifier: Topic :: Utilities
Classifier: License :: OSI Approved :: BSD License
Classifier: Operating System :: OS Independent
Classifier: Programming Language :: Python
